sipro/__init__.py
sipro-1.0.1.dist-info/LICENSE.txt
sipro-1.0.1.dist-info/METADATA
sipro-1.0.1.dist-info/WHEEL
sipro-1.0.1.dist-info/top_level.txt
sipro-1.0.1.dist-info/RECORD
