Metadata-Version: 2.1
Name: sipro
Version: 1.0.1
Summary: A very simple profiler for Python.
Home-page: https://github.com/eliasffyksen/sipro
Author: Elias F. Fyksen
Author-email: github@fyksen.net
License: MIT
Classifier: Programming Language :: Python :: 3
Classifier: License :: OSI Approved :: MIT License
Classifier: Operating System :: OS Independent
Requires-Python: >=3.10
License-File: LICENSE.txt
